schoginitoys/__init__.py
schoginitoys/schoginitoys.py
schoginitoys-1.1.9.dist-info/LICENSE.txt
schoginitoys-1.1.9.dist-info/METADATA
schoginitoys-1.1.9.dist-info/WHEEL
schoginitoys-1.1.9.dist-info/top_level.txt
schoginitoys-1.1.9.dist-info/RECORD
