Metadata-Version: 2.1
Name: schoginitoys
Version: 1.1.9
Summary: Schogini Toys DIY Kit Toolkit designed for electronics and coding
Home-page: https://schogini.com
Author: Sreeprakash Neelakantan
Author-email: sree@schogini.com
License: Proprietary
Platform: UNKNOWN
Classifier: Development Status :: 5 - Production/Stable
Classifier: Intended Audience :: End Users/Desktop
Classifier: License :: Other/Proprietary License
Classifier: Natural Language :: English
Classifier: Programming Language :: Python :: Implementation :: MicroPython
Classifier: Topic :: Software Development :: Libraries :: Python Modules
License-File: LICENSE.txt
